<?xml version="1.0" encoding="UTF-8"?>
<!DOCTYPE mapper PUBLIC "-//mybatis.org//DTD Mapper 3.0//EN" "http://mybatis.org/dtd/mybatis-3-mapper.dtd">
<mapper namespace="com.ccclubs.pub.orm.mapper.SrvGroupMapper">
  <resultMap id="BaseResultMap" type="com.ccclubs.pub.orm.model.SrvGroup">
    <!--
      WARNING - @mbg.generated
      This element is automatically generated by MyBatis Generator, do not modify.
    -->
    <id column="sg_id" jdbcType="BIGINT" property="sgId" />
    <result column="sg_name" jdbcType="VARCHAR" property="sgName" />
    <result column="sg_parent_id" jdbcType="BIGINT" property="sgParentId" />
    <result column="sg_family" jdbcType="VARCHAR" property="sgFamily" />
    <result column="sg_flag" jdbcType="VARCHAR" property="sgFlag" />
    <result column="sg_status" jdbcType="SMALLINT" property="sgStatus" />
  </resultMap>
  <sql id="Example_Where_Clause">
    <!--
      WARNING - @mbg.generated
      This element is automatically generated by MyBatis Generator, do not modify.
    -->
    <where>
      <foreach collection="oredCriteria" item="criteria" separator="or">
        <if test="criteria.valid">
          <trim prefix="(" prefixOverrides="and" suffix=")">
            <foreach collection="criteria.criteria" item="criterion">
              <choose>
                <when test="criterion.noValue">
                  and ${criterion.condition}
                </when>
                <when test="criterion.singleValue">
                  and ${criterion.condition} #{criterion.value}
                </when>
                <when test="criterion.betweenValue">
                  and ${criterion.condition} #{criterion.value} and #{criterion.secondValue}
                </when>
                <when test="criterion.listValue">
                  and ${criterion.condition}
                  <foreach close=")" collection="criterion.value" item="listItem" open="(" separator=",">
                    #{listItem}
                  </foreach>
                </when>
              </choose>
            </foreach>
          </trim>
        </if>
      </foreach>
    </where>
  </sql>
  <sql id="Update_By_Example_Where_Clause">
    <!--
      WARNING - @mbg.generated
      This element is automatically generated by MyBatis Generator, do not modify.
    -->
    <where>
      <foreach collection="example.oredCriteria" item="criteria" separator="or">
        <if test="criteria.valid">
          <trim prefix="(" prefixOverrides="and" suffix=")">
            <foreach collection="criteria.criteria" item="criterion">
              <choose>
                <when test="criterion.noValue">
                  and ${criterion.condition}
                </when>
                <when test="criterion.singleValue">
                  and ${criterion.condition} #{criterion.value}
                </when>
                <when test="criterion.betweenValue">
                  and ${criterion.condition} #{criterion.value} and #{criterion.secondValue}
                </when>
                <when test="criterion.listValue">
                  and ${criterion.condition}
                  <foreach close=")" collection="criterion.value" item="listItem" open="(" separator=",">
                    #{listItem}
                  </foreach>
                </when>
              </choose>
            </foreach>
          </trim>
        </if>
      </foreach>
    </where>
  </sql>
  <sql id="Base_Column_List">
    <!--
      WARNING - @mbg.generated
      This element is automatically generated by MyBatis Generator, do not modify.
    -->
    sg_id, sg_name, sg_parent_id, sg_family, sg_flag, sg_status
  </sql>
  <select id="selectByExample" parameterType="com.ccclubs.pub.orm.model.SrvGroupExample" resultMap="BaseResultMap">
    <!--
      WARNING - @mbg.generated
      This element is automatically generated by MyBatis Generator, do not modify.
    -->
    select
    <if test="distinct">
      distinct
    </if>
    <include refid="Base_Column_List" />
    from srv_group
    <if test="_parameter != null">
      <include refid="Example_Where_Clause" />
    </if>
    <if test="orderByClause != null">
      order by ${orderByClause}
    </if>
  </select>
  <select id="selectByPrimaryKey" parameterType="java.lang.Long" resultMap="BaseResultMap">
    <!--
      WARNING - @mbg.generated
      This element is automatically generated by MyBatis Generator, do not modify.
    -->
    select 
    <include refid="Base_Column_List" />
    from srv_group
    where sg_id = #{sgId,jdbcType=BIGINT}
  </select>
  <delete id="deleteByPrimaryKey" parameterType="java.lang.Long">
    <!--
      WARNING - @mbg.generated
      This element is automatically generated by MyBatis Generator, do not modify.
    -->
    delete from srv_group
    where sg_id = #{sgId,jdbcType=BIGINT}
  </delete>
  <delete id="deleteByExample" parameterType="com.ccclubs.pub.orm.model.SrvGroupExample">
    <!--
      WARNING - @mbg.generated
      This element is automatically generated by MyBatis Generator, do not modify.
    -->
    delete from srv_group
    <if test="_parameter != null">
      <include refid="Example_Where_Clause" />
    </if>
  </delete>
  <insert id="insert" parameterType="com.ccclubs.pub.orm.model.SrvGroup">
    <!--
      WARNING - @mbg.generated
      This element is automatically generated by MyBatis Generator, do not modify.
    -->
    insert into srv_group (sg_id, sg_name, sg_parent_id, 
      sg_family, sg_flag, sg_status
      )
    values (#{sgId,jdbcType=BIGINT}, #{sgName,jdbcType=VARCHAR}, #{sgParentId,jdbcType=BIGINT}, 
      #{sgFamily,jdbcType=VARCHAR}, #{sgFlag,jdbcType=VARCHAR}, #{sgStatus,jdbcType=SMALLINT}
      )
  </insert>
  <insert id="insertSelective" parameterType="com.ccclubs.pub.orm.model.SrvGroup">
    <!--
      WARNING - @mbg.generated
      This element is automatically generated by MyBatis Generator, do not modify.
    -->
    insert into srv_group
    <trim prefix="(" suffix=")" suffixOverrides=",">
      <if test="sgId != null">
        sg_id,
      </if>
      <if test="sgName != null">
        sg_name,
      </if>
      <if test="sgParentId != null">
        sg_parent_id,
      </if>
      <if test="sgFamily != null">
        sg_family,
      </if>
      <if test="sgFlag != null">
        sg_flag,
      </if>
      <if test="sgStatus != null">
        sg_status,
      </if>
    </trim>
    <trim prefix="values (" suffix=")" suffixOverrides=",">
      <if test="sgId != null">
        #{sgId,jdbcType=BIGINT},
      </if>
      <if test="sgName != null">
        #{sgName,jdbcType=VARCHAR},
      </if>
      <if test="sgParentId != null">
        #{sgParentId,jdbcType=BIGINT},
      </if>
      <if test="sgFamily != null">
        #{sgFamily,jdbcType=VARCHAR},
      </if>
      <if test="sgFlag != null">
        #{sgFlag,jdbcType=VARCHAR},
      </if>
      <if test="sgStatus != null">
        #{sgStatus,jdbcType=SMALLINT},
      </if>
    </trim>
  </insert>
  <select id="countByExample" parameterType="com.ccclubs.pub.orm.model.SrvGroupExample" resultType="java.lang.Long">
    <!--
      WARNING - @mbg.generated
      This element is automatically generated by MyBatis Generator, do not modify.
    -->
    select count(*) from srv_group
    <if test="_parameter != null">
      <include refid="Example_Where_Clause" />
    </if>
  </select>
  <update id="updateByExampleSelective" parameterType="map">
    <!--
      WARNING - @mbg.generated
      This element is automatically generated by MyBatis Generator, do not modify.
    -->
    update srv_group
    <set>
      <if test="record.sgId != null">
        sg_id = #{record.sgId,jdbcType=BIGINT},
      </if>
      <if test="record.sgName != null">
        sg_name = #{record.sgName,jdbcType=VARCHAR},
      </if>
      <if test="record.sgParentId != null">
        sg_parent_id = #{record.sgParentId,jdbcType=BIGINT},
      </if>
      <if test="record.sgFamily != null">
        sg_family = #{record.sgFamily,jdbcType=VARCHAR},
      </if>
      <if test="record.sgFlag != null">
        sg_flag = #{record.sgFlag,jdbcType=VARCHAR},
      </if>
      <if test="record.sgStatus != null">
        sg_status = #{record.sgStatus,jdbcType=SMALLINT},
      </if>
    </set>
    <if test="_parameter != null">
      <include refid="Update_By_Example_Where_Clause" />
    </if>
  </update>
  <update id="updateByExample" parameterType="map">
    <!--
      WARNING - @mbg.generated
      This element is automatically generated by MyBatis Generator, do not modify.
    -->
    update srv_group
    set sg_id = #{record.sgId,jdbcType=BIGINT},
      sg_name = #{record.sgName,jdbcType=VARCHAR},
      sg_parent_id = #{record.sgParentId,jdbcType=BIGINT},
      sg_family = #{record.sgFamily,jdbcType=VARCHAR},
      sg_flag = #{record.sgFlag,jdbcType=VARCHAR},
      sg_status = #{record.sgStatus,jdbcType=SMALLINT}
    <if test="_parameter != null">
      <include refid="Update_By_Example_Where_Clause" />
    </if>
  </update>
  <update id="updateByPrimaryKeySelective" parameterType="com.ccclubs.pub.orm.model.SrvGroup">
    <!--
      WARNING - @mbg.generated
      This element is automatically generated by MyBatis Generator, do not modify.
    -->
    update srv_group
    <set>
      <if test="sgName != null">
        sg_name = #{sgName,jdbcType=VARCHAR},
      </if>
      <if test="sgParentId != null">
        sg_parent_id = #{sgParentId,jdbcType=BIGINT},
      </if>
      <if test="sgFamily != null">
        sg_family = #{sgFamily,jdbcType=VARCHAR},
      </if>
      <if test="sgFlag != null">
        sg_flag = #{sgFlag,jdbcType=VARCHAR},
      </if>
      <if test="sgStatus != null">
        sg_status = #{sgStatus,jdbcType=SMALLINT},
      </if>
    </set>
    where sg_id = #{sgId,jdbcType=BIGINT}
  </update>
  <update id="updateByPrimaryKey" parameterType="com.ccclubs.pub.orm.model.SrvGroup">
    <!--
      WARNING - @mbg.generated
      This element is automatically generated by MyBatis Generator, do not modify.
    -->
    update srv_group
    set sg_name = #{sgName,jdbcType=VARCHAR},
      sg_parent_id = #{sgParentId,jdbcType=BIGINT},
      sg_family = #{sgFamily,jdbcType=VARCHAR},
      sg_flag = #{sgFlag,jdbcType=VARCHAR},
      sg_status = #{sgStatus,jdbcType=SMALLINT}
    where sg_id = #{sgId,jdbcType=BIGINT}
  </update>
</mapper>